MANIFEST.in
README.txt
setup.py
MerlotTemplates.egg-info/PKG-INFO
MerlotTemplates.egg-info/SOURCES.txt
MerlotTemplates.egg-info/dependency_links.txt
MerlotTemplates.egg-info/entry_points.txt
MerlotTemplates.egg-info/namespace_packages.txt
MerlotTemplates.egg-info/not-zip-safe
MerlotTemplates.egg-info/requires.txt
MerlotTemplates.egg-info/top_level.txt
docs/HISTORY.txt
merlot/__init__.py
merlot/templates/__init__.py
merlot/templates/merlot_buildout.py
merlot/templates/merlot_buildout/bootstrap.py
merlot/templates/merlot_buildout/buildout.cfg_tmpl
merlot/templates/merlot_buildout/etc/README.txt
merlot/templates/merlot_buildout/etc/debug.ini.in
merlot/templates/merlot_buildout/etc/deploy.ini.in
merlot/templates/merlot_buildout/etc/merlot_server.in
merlot/templates/merlot_buildout/etc/site.zcml.in
merlot/templates/merlot_buildout/etc/zope.conf.in