Metadata-Version: 1.0
Name: MerlotTemplates
Version: 0.2
Summary: Paster templates for Merlot
Home-page: http://code.google.com/p/merlot/
Author: Emanuel Sartor
Author-email: emanuel@menttes.com
License: GPL2
Keywords: grok merlot project management
Platform: UNKNOWN
Classifier: Programming Language :: Python
